catsart/__init__.py
catsart/__main__.py
catsart/database/__init__.py
catsart/database/asciione.json
catsart/database/asciitwo.json
catsart-7.0.dist-info/LICENSE.txt
catsart-7.0.dist-info/METADATA
catsart-7.0.dist-info/WHEEL
catsart-7.0.dist-info/entry_points.txt
catsart-7.0.dist-info/top_level.txt
catsart-7.0.dist-info/RECORD
